MANIFEST.in
README.rst
setup.py
dna/__init__.py
dna/dna.py
dna/data/huff3.dict
file2dna.egg-info/PKG-INFO
file2dna.egg-info/SOURCES.txt
file2dna.egg-info/dependency_links.txt
file2dna.egg-info/entry_points.txt
file2dna.egg-info/top_level.txt