Metadata-Version: 1.1
Name: file2dna
Version: 0.4
Summary: A script to encode/decode arbitrary computer files into DNA sequences.
Home-page: https://github.com/allanino/DNA
Author: Allan Inocencio de Souza Costa
Author-email: allaninocencio@yahoo.com.br
License: MIT
Keywords: dna encoding decoding file
Platform: UNKNOWN
Classifier: License :: OSI Approved :: MIT License
Classifier: Programming Language :: Python :: 2.6
Classifier: Programming Language :: Python :: 2.7
